nonebot_plugin_lagrange/.DS_Store
nonebot_plugin_lagrange/__init__.py
nonebot_plugin_lagrange/config.py
nonebot_plugin_lagrange/globals.py
nonebot_plugin_lagrange/lagrange.py
nonebot_plugin_lagrange/manager.py
nonebot_plugin_lagrange/network.py
nonebot_plugin_lagrange/servers.py
nonebot_plugin_lagrange/utils.py
nonebot_plugin_lagrange/webui/index.css
nonebot_plugin_lagrange/webui/index.html
nonebot_plugin_lagrange/webui/index.js
nonebot_plugin_lagrange-1.1.0.dist-info/LICENSE
nonebot_plugin_lagrange-1.1.0.dist-info/METADATA
nonebot_plugin_lagrange-1.1.0.dist-info/WHEEL
nonebot_plugin_lagrange-1.1.0.dist-info/RECORD
