Metadata-Version: 2.3
Name: nonebot_plugin_lagrange
Version: 1.1.0
Summary: 一款便于管理 Lagrange.Onebot 的插件。
License: GPL3
Keywords: nonebot,nonebot2,lagrange.onebot,lagrange,onebot v11,onebot
Author: Lonely-Sails
Requires-Python: >=3.8,<4.0
Classifier: License :: Other/Proprietary License
Classifier: Programming Language :: Python :: 3
Classifier: Programming Language :: Python :: 3.8
Classifier: Programming Language :: Python :: 3.9
Classifier: Programming Language :: Python :: 3.10
Classifier: Programming Language :: Python :: 3.11
Classifier: Programming Language :: Python :: 3.12
Classifier: Programming Language :: Python :: 3.13
Provides-Extra: onebot
Requires-Dist: httpx (>=0.27.0,<0.28.0)
Requires-Dist: nonebot-adapter-onebot (>=2.0.0-beta.1,<3.0.0) ; extra == "onebot"
Requires-Dist: nonebot-plugin-localstore (>=0.7.0,<0.8.0)
Requires-Dist: nonebot2 (>=2.2.0,<3.0.0)
Project-URL: Documentation, https://github.com/Lonely-Sails/nonebot-plugin-lagrange#readme
Project-URL: Homepage, https://github.com/Lonely-Sails/nonebot-plugin-lagrange
Project-URL: Repository, https://github.com/Lonely-Sails/nonebot-plugin-lagrange
